{
  "1": {
    "id": "1",
    "title": "Рождение Венеры",
    "author": "Сандро Боттичелли",
    "oldPrice": "2 000 000",
    "price": "1 000 000",
    "img": [
      "card1_1",
      "card1_2",
      "card1_3",
      "card1_4"
    ],
    "sold": false,
    "info": "«Рождение Венеры» (итал. La Nascita di Venere) — картина выдающегося итальянского живописца периода кватроченто (раннего итальянского Возрождения) флорентийской школы Сандро Боттичелли. Написана темперой на холсте, а не на дереве, как обычно, из-за её большого размера (172,5 × 278,5 см) между 1482 и 1486 годами. Хранится в галерее Уффици, Флоренция."
  },
  "2": {
    "id": "2",
    "title": "Тайная вечеря",
    "author": "Леонардо да Винчи",
    "oldPrice": null,
    "price": "1 000 000",
    "img": [
      "card2_1",
      "card2_2",
      "card2_3",
      "card2_4"
    ],
    "sold": false,
    "info": "«Та́йная ве́черя» (итал. Il Cenacolo или L’Ultima Cena) — монументальная роспись работы Леонардо да Винчи, изображающая сцену последней трапезы Христа со своими учениками. Создана в 1495—1498 годы в доминиканском монастыре Санта-Мария-делле-Грацие в Милане."
  },
  "3": {
    "id": "3",
    "title": "Сотворение Адама",
    "author": "Микеланджело",
    "oldPrice": "6 000 000",
    "price": "5 000 000",
    "img": [
      "card3_1",
      "card3_2",
      "card3_3",
      "card3_4"
    ],
    "sold": false,
    "info": "«Сотворение Адама» (итал. La creazione di Adamo) - фреска Микеланджело Буонарроти на потолке Сикстинской капеллы (Ватикан), созданная им около 1511-1512 лет. Это - одна из центральных композиций, иллюстрирующую создании человека Богом."
  },
  "4": {
    "id": "4",
    "title": "Урок анатомии",
    "author": "Рембрандт",
    "oldPrice": null,
    "price": null,
    "img": [
      "card4_1",
      "card4_2",
      "card4_3",
      "card4_4"
    ],
    "sold": true,
    "info": "«Урок анатомии доктора Тульпа» — картина выдающегося голландского живописца Рембрандта ван Рейна, написанная в 1632 году."
  }
}